syshelper/__init__.py
syshelper/syshelper.py
syshelper-0.0.6.dist-info/METADATA
syshelper-0.0.6.dist-info/WHEEL
syshelper-0.0.6.dist-info/top_level.txt
syshelper-0.0.6.dist-info/RECORD
