Metadata-Version: 2.1
Name: syshelper
Version: 0.0.6
Requires-Dist: logclshelper
